README.rst
setup.py
awesome_slugify.egg-info/PKG-INFO
awesome_slugify.egg-info/SOURCES.txt
awesome_slugify.egg-info/dependency_links.txt
awesome_slugify.egg-info/requires.txt
awesome_slugify.egg-info/top_level.txt
slugify/__init__.py
slugify/main.py
slugify/tests.py