Metadata-Version: 1.1
Name: awesome-slugify
Version: 1.2.3
Summary: Python flexible slugify module
Home-page: https://github.com/dimka665/awesome-slugify
Author: Dmitry Voronin
Author-email: dimka665@gmail.com
License: GNU GPLv3
Keywords: slugify alternative russian slugify flexible awesome
Platform: UNKNOWN
Classifier: License :: OSI Approved :: GNU General Public License v3 (GPLv3)
Classifier: Programming Language :: Python
Classifier: Programming Language :: Python :: 2
Classifier: Programming Language :: Python :: 2.6
Classifier: Programming Language :: Python :: 2.7
Classifier: Programming Language :: Python :: 3
Classifier: Programming Language :: Python :: 3.3
